<?xml version="1.0" encoding="UTF-8"?>
<material name="transform" pass_projection_matrix="true" pass_view_matrix="true" pass_model_matrix="true">
	<texture order="0" name="grass" src="Grass.jpg" />
	<texture order="1" name="normal_map" src="NormalMap.jpg" />
	<effect src="Shader.fx">
		<attributes>
			<attribute name="bool_param" value="bool(true)" />
			<attribute name="int_param" value="float(1)" />
			<attribute name="float_param" value="float(1.0f)" />
			<attribute name="vec3_param" value="vec3(1, 0, 0)" />
			<attribute name="vec4_param" value="vec4(1, 0, 0, 0)" />
			<attribute name="mat44_param" value="mat44(1, 0, 0, 0; 0, 1, 0, 0; 0, 0, 1, 0; 0, 0, 0, 1)" />
		</attributes>
	</effect>
</material>